{
  "branding": {
    "accent_color": "FF1565C0",
    "tagline": "Stream everything. SoLo simple."
  },
  "build": {
    "description": "SoLo-branded streaming build \u2014 movies, TV, live channels, and Real-Debrid-ready add-ons via the SoLoTV repository.",
    "id": "solotv",
    "name": "SoLoTV",
    "version": "1.0.5"
  },
  "build_type": "streaming",
  "card_image": "solotv.png",
  "content_addons": [],
  "favourites": [
    {
      "action": "RunAddon(plugin.program.solokodi.setup)",
      "name": "SoLoTV Setup"
    },
    {
      "action": "RunAddon(plugin.program.chef21)",
      "name": "SoLoTV Build Wizard"
    }
  ],
  "generated_at": "2026-05-31T23:03:02Z",
  "manifest_url": "https://solokodi.sololink.cloud/builds/solotv/manifest.json",
  "repository": {
    "id": "repository.solokodi",
    "name": "SoLoKodi Repository",
    "url": "https://solokodi.sololink.cloud/repo/addons.xml",
    "version": "0.5.0"
  },
  "repository_id": "repository.solokodi",
  "requires_debrid": true,
  "setup_addon": {
    "id": "plugin.program.solokodi.setup",
    "name": "SoLoKodi Setup",
    "version": "0.5.8"
  },
  "setup_favourite": "SoLoTV Setup",
  "skin": {
    "apply_on_setup": false,
    "colors": [
      [
        "lookandfeel.skincolors",
        "FF1565C0"
      ]
    ],
    "default_id": "skin.estuary"
  },
  "solokodi_addons": [],
  "streaming_repo": {
    "build_list_url": "https://solokodi.sololink.cloud/solotv/builds.xml",
    "changelog_dir": "https://solokodi.sololink.cloud/solotv/",
    "file_source_name": "solotv",
    "file_source_url": "https://solokodi.sololink.cloud/solotv/",
    "notify_url": "https://solokodi.sololink.cloud/solotv/notify.txt",
    "recommended_build_hint": "In the SoLoTV wizard, choose the SoLoTV 4K build for the full interface.",
    "repository_id": "repository.solotv",
    "repository_zip": "repository.solotv-1.0.1.zip",
    "videos_url": "https://solokodi.sololink.cloud/solotv/videos.txt",
    "wizard_addon_id": "plugin.program.chef21",
    "wizard_label": "SoLoTV Build Wizard"
  },
  "tagline": "Stream everything. SoLo simple.",
  "website": "https://solokodi.sololink.cloud/solotv/",
  "wizard_steps": [
    {
      "id": "solotv_repo",
      "label": "Install SoLoTV repository",
      "required": true
    },
    {
      "id": "solotv_wizard",
      "label": "Install SoLoTV Build Wizard",
      "required": true
    },
    {
      "id": "favourites",
      "label": "Create SoLoTV shortcuts",
      "required": true
    },
    {
      "id": "realdebrid",
      "label": "Connect Real-Debrid (optional)",
      "required": false
    },
    {
      "id": "trakt",
      "label": "Authorize Trakt (optional)",
      "required": false
    },
    {
      "id": "tmdb",
      "label": "Add TMDb API key (optional)",
      "required": false
    },
    {
      "id": "launch_wizard",
      "label": "Install SoLoTV interface",
      "required": true
    }
  ]
}
